<?xml version="1.0" encoding="utf-8" ?>
<dwsync>
<file name="do_login.php" server="management.casino-del-mundo.com:2288//home/casino-del-mundo.com/www/" local="130201711867081103" remote="130201712350000000" Dst="2" />
<file name="friend_register.php" server="management.casino-del-mundo.com:2288//home/casino-del-mundo.com/www/" local="130082569529815343" remote="130201712330000000" Dst="2" />
<file name="do_register.php" server="management.casino-del-mundo.com:2288//home/casino-del-mundo.com/www/" local="130201712024673003" remote="130201712340000000" Dst="2" />
<file name="do_activate.php" server="management.casino-del-mundo.com:2288//home/casino-del-mundo.com/www/" local="130201711163747803" remote="130201712370000000" Dst="2" />
<file name="do_activate.php" server="185.24.97.234:8916/casino/" local="130282412975554148" remote="130282483570000000" Dst="1" />
<file name="do_login.php" server="185.24.97.234:8916/casino/" local="130290878237120484" remote="130290948200000000" Dst="1" />
<file name="do_register.php" server="185.24.97.234:8916/casino/" local="130290776378979821" remote="130290846590000000" Dst="1" />
<file name="friend_register.php" server="185.24.97.234:8916/casino/" local="130280603579350107" remote="130280674220000000" Dst="1" />
</dwsync>